[
    {
        "model": "roster.preferenceset",
        "pk": 1,
        "fields": {
            "name": "default_display",
            "description": "Default Clusive display preference set",
            "prefs_json": "{\"fluid_prefs_contrast\":\"default\",\"fluid_prefs_textFont\":\"default\",\"fluid_prefs_textSize\":1,\"fluid_prefs_lineSpace\":1.6,\"fluid_prefs_letterSpace\":1,\"cisl_prefs_glossary\":true}"
        }
    },
    {
        "model": "roster.preferenceset",
        "pk": 2,
        "fields": {
            "name": "default_reading_tools",
            "description": "Default Clusive reading tools preference set",
            "prefs_json": "{\"cisl_prefs_readSpeed\":1.0,\"cisl_prefs_readVoices\":[]}"
        }
    }    
]